Metadata-Version: 2.1
Name: solvation-analysis
Version: 0.4.1
Summary: A toolkit to analyze solvation structure in molecular dynamics trajectories.
Author: Orion Cohen
Author-email: Orion Cohen <orioncohen@berkeley.edu>
Maintainer-email: Orion Cohen <orioncohen@berkeley.edu>, Hugo MacDermott-Opeskin <hugomacdermott@gmail.com>
License: GNU GENERAL PUBLIC LICENSE 
Project-URL: Documentation, https://solvation-analysis.readthedocs.io
Project-URL: Issue Tracker, https://github.com/MDAnalysis/solvation-analysis/issues
Project-URL: Source, https://github.com/MDAnalysis/solvation-analysis
Keywords: python,science,chemistry,biophysics,molecular-dynamics,computational-chemistry,molecular-simulation,analysis,trajectory-analysis,solvation
Classifier: Development Status :: 3 - Alpha
Classifier: Environment :: Console
Classifier: Intended Audience :: Science/Research
Classifier: License :: OSI Approved :: GNU General Public License v2 or later (GPLv2+)
Classifier: Operating System :: POSIX
Classifier: Operating System :: MacOS :: MacOS X
Classifier: Operating System :: Microsoft :: Windows
Classifier: Programming Language :: Python
Classifier: Programming Language :: Python :: 3.8
Classifier: Programming Language :: Python :: 3.9
Classifier: Programming Language :: Python :: 3.10
Classifier: Programming Language :: Python :: 3.11
Classifier: Topic :: Scientific/Engineering
Classifier: Topic :: Scientific/Engineering :: Bio-Informatics
Classifier: Topic :: Scientific/Engineering :: Chemistry
Classifier: Topic :: Software Development :: Libraries :: Python Modules
Requires-Python: >=3.8
License-File: LICENSE
Requires-Dist: numpy >=1.20.0
Requires-Dist: pandas >=2.2
Requires-Dist: mdanalysis >=2.0.0
Requires-Dist: pytest
Requires-Dist: matplotlib
Requires-Dist: setuptools
Requires-Dist: scipy
Requires-Dist: statsmodels
Requires-Dist: plotly
Requires-Dist: rdkit
